Workbook

Sheet Parameters
A1: TECHNICAL & COMMERCIAL PARAMETERS
A3: Parameter | B3: Value | C3: Unit | D3: Notes
A4: Default commercial margin | B4: 0.3 | C4: % | D4: Applied to cost to get selling price
A5: VAT rate (Spain) | B5: 0.21 | C5: % | D5: Standard IVA
A6: Snow load (Sitges - coastal) | B6: 0.4 | C6: kN/m2 | D6: Eurocode 1 - low-elevation coastal
A7: Standard floor height | B7: 2.8 | C7: m | D7: Used to derive wall surface from length
A8: External wall thickness (X-lam) | B8: 140 | C8: mm | D8: Default panel choice
A9: Internal wall thickness (X-lam) | B9: 100 | C9: mm | D9: Load-bearing internal walls
A10: Wood-fibre insulation - walls | B10: 200 | C10: mm | D10: Standard envelope
A11: Wood-fibre insulation - roof | B11: 240 | C11: mm | D11: Standard roof package
A12: Terrace commercial coefficient | B12: 0.3 | C12: % | D12: m2 terrace counted at 30% commercial
A13: Roof commercial coefficient | B13: 0 | C13: % | D13: Roof area not commercial
A14: Site duration (assumption) | B14: 3 | C14: months | D14: Crane + scaffolding rental basis
A17: Cells in green are inputs (you can change them); other sheets recompute automatically.

Sheet Schedule
A1: BUILDING SCHEDULE (quantities derived from project geometry)
A2: Green cells = inputs to edit | Yellow cells = computed
A3: A. Per-floor data (input)
A4: Floor | B4: Habitable area m2 | C4: Terrace area m2 | D4: Ext. perimeter (m) | E4: Int. walls length (m) | F4: Floor height (m) | G4: Notes
A5: P0 - Ground floor | B5: 115 | C5: 0 | D5: 48 | E5: 32 | F5: =Parameters!$B$7 | G5: Living + kitchen + 1 bedroom
A6: P1 - First floor | B6: 110 | C6: 30 | D6: 46 | E6: 30 | F6: =Parameters!$B$7 | G6: 3 bedrooms + 2 bathrooms
A7: P2 - Attic / technical | B7: 15 | C7: 0 | D7: 12 | E7: 0 | F7: 1.5 | G7: Low technical floor
A8: TOTAL | B8: =SUM(B5:B7) | C8: =SUM(C5:C7) | D8: =SUM(D5:D7) | E8: =SUM(E5:E7)
A10: B. Roof data (input)
A11: Roof projected area (m2) | B11: 150
A12: Gutter + downpipe length (m) | B12: 38
A14: C. Windows and openings (input)
A15: Total window area (m2) | B15: 43
A16: Number of shutters (units) | B16: 14
A17: Entrance doors (units) | B17: 1
A19: D. Derived quantities (auto-computed)
A20: External wall surface (m2) | B20: =SUMPRODUCT(D5:D7,F5:F7) | G20: SUMPRODUCT(perimeter, height) over all floors
A21: Internal wall surface (m2) | B21: =SUMPRODUCT(E5:E7,F5:F7) | G21: SUMPRODUCT(int_length, height)
A22: Intermediate slab area (m2) | B22: =SUM(B6:B7) | G22: habitable area of floors above ground
A23: Commercial area (m2) | B23: =B8+C8*Parameters!$B$12 | G23: habitable + terrace * coeff (from Parameters)
A24: Std glulam beams - total length (m) | B24: =B22*0.18 | G24: rough rule: 0.18 m of beam per m2 of slab
A25: Large-span beams - length (m) | B25: 8 | G25: manual input - depends on living-room span

Sheet PriceList
A1: PRICE LIST (cost prices, EUR)
A3: Code | B3: Category | C3: Description | D3: Unit | E3: Unit Price EUR
A4: STR-001 | B4: STR | C4: X-lam wall panel 140 mm (external load-bearing) | D4: m2 | E4: 285
A5: STR-002 | B5: STR | C5: X-lam wall panel 100 mm (internal load-bearing) | D5: m2 | E5: 230
A6: STR-010 | B6: STR | C6: GL24h glulam beam 200x400 | D6: m | E6: 165
A7: STR-011 | B7: STR | C7: GL24h glulam beam 240x480 (large spans) | D7: m | E7: 245
A8: STR-020 | B8: STR | C8: X-lam intermediate slab 200 mm | D8: m2 | E8: 315
A9: STR-021 | B9: STR | C9: X-lam roof slab 160 mm | D9: m2 | E9: 295
A10: ENV-001 | B10: ENV | C10: Wood-fibre insulation 200 mm (walls) | D10: m2 | E10: 78
A11: ENV-002 | B11: ENV | C11: Wood-fibre insulation 240 mm (roof) | D11: m2 | E11: 92
A12: ENV-003 | B12: ENV | C12: Ventilated facade - larch cladding | D12: m2 | E12: 145
A13: ENV-004 | B13: ENV | C13: Ceramic tile roof package (membrane + tiles) | D13: m2 | E13: 95
A14: ENV-005 | B14: ENV | C14: Aluminium flashings and gutter set | D14: m | E14: 48
A15: WIN-001 | B15: WIN | C15: Aluminium-clad timber window, triple glazing | D15: m2 | E15: 720
... A21: SITE-20 | B21: SITE | C21: On-site assembly labour | D21: day | E21: 780

Sheet Computo
A1: QUOTE COMPUTATION (cascading from Schedule + PriceList + Parameters)
A2: Code is the only manual lookup. Description, Category, Unit Price are pulled by VLOOKUP. Quantities reference the Schedule sheet.
A4: Code | B4: Description (auto) | C4: Cat (auto) | D4: Qty | E4: Unit | F4: Unit Price (auto) | G4: Total
A5: STR-001 | B5: =VLOOKUP(A5,PriceList!$A$4:$E$21,3,FALSE) | C5: =VLOOKUP(A5,PriceList!$A$4:$E$21,2,FALSE) | D5: =Schedule!$B$20 | E5: =VLOOKUP(A5,PriceList!$A$4:$E$21,4,FALSE) | F5: =VLOOKUP(A5,PriceList!$A$4:$E$21,5,FALSE) | G5: =D5*F5
A6: STR-002 | B6: =VLOOKUP(A6,PriceList!$A$4:$E$21,3,FALSE) | C6: =VLOOKUP(A6,PriceList!$A$4:$E$21,2,FALSE) | D6: =Schedule!$B$21 | E6: =VLOOKUP(A6,PriceList!$A$4:$E$21,4,FALSE) | F6: =VLOOKUP(A6,PriceList!$A$4:$E$21,5,FALSE) | G6: =D6*F6
A7: STR-010 | B7: =VLOOKUP(A7,PriceList!$A$4:$E$21,3,FALSE) | C7: =VLOOKUP(A7,PriceList!$A$4:$E$21,2,FALSE) | D7: =Schedule!$B$24 | E7: =VLOOKUP(A7,PriceList!$A$4:$E$21,4,FALSE) | F7: =VLOOKUP(A7,PriceList!$A$4:$E$21,5,FALSE) | G7: =D7*F7
A8: STR-011 | B8: =VLOOKUP(A8,PriceList!$A$4:$E$21,3,FALSE) | C8: =VLOOKUP(A8,PriceList!$A$4:$E$21,2,FALSE) | D8: =Schedule!$B$25 | E8: =VLOOKUP(A8,PriceList!$A$4:$E$21,4,FALSE) | F8: =VLOOKUP(A8,PriceList!$A$4:$E$21,5,FALSE) | G8: =D8*F8
A9: STR-020 | B9: =VLOOKUP(A9,PriceList!$A$4:$E$21,3,FALSE) | C9: =VLOOKUP(A9,PriceList!$A$4:$E$21,2,FALSE) | D9: =Schedule!$B$22 | E9: =VLOOKUP(A9,PriceList!$A$4:$E$21,4,FALSE) | F9: =VLOOKUP(A9,PriceList!$A$4:$E$21,5,FALSE) | G9: =D9*F9
A10: STR-021 | B10: =VLOOKUP(A10,PriceList!$A$4:$E$21,3,FALSE) | C10: =VLOOKUP(A10,PriceList!$A$4:$E$21,2,FALSE) | D10: =Schedule!$B$11 | E10: =VLOOKUP(A10,PriceList!$A$4:$E$21,4,FALSE) | F10: =VLOOKUP(A10,PriceList!$A$4:$E$21,5,FALSE) | G10: =D10*F10
A11: ENV-001 | B11: =VLOOKUP(A11,PriceList!$A$4:$E$21,3,FALSE) | C11: =VLOOKUP(A11,PriceList!$A$4:$E$21,2,FALSE) | D11: =Schedule!$B$20 | E11: =VLOOKUP(A11,PriceList!$A$4:$E$21,4,FALSE) | F11: =VLOOKUP(A11,PriceList!$A$4:$E$21,5,FALSE) | G11: =D11*F11
A12: ENV-002 | B12: =VLOOKUP(A12,PriceList!$A$4:$E$21,3,FALSE) | C12: =VLOOKUP(A12,PriceList!$A$4:$E$21,2,FALSE) | D12: =Schedule!$B$11 | E12: =VLOOKUP(A12,PriceList!$A$4:$E$21,4,FALSE) | F12: =VLOOKUP(A12,PriceList!$A$4:$E$21,5,FALSE) | G12: =D12*F12
A13: ENV-003 | B13: =VLOOKUP(A13,PriceList!$A$4:$E$21,3,FALSE) | C13: =VLOOKUP(A13,PriceList!$A$4:$E$21,2,FALSE) | D13: =Schedule!$B$20 | E13: =VLOOKUP(A13,PriceList!$A$4:$E$21,4,FALSE) | F13: =VLOOKUP(A13,PriceList!$A$4:$E$21,5,FALSE) | G13: =D13*F13
A14: ENV-004 | B14: =VLOOKUP(A14,PriceList!$A$4:$E$21,3,FALSE) | C14: =VLOOKUP(A14,PriceList!$A$4:$E$21,2,FALSE) | D14: =Schedule!$B$11 | E14: =VLOOKUP(A14,PriceList!$A$4:$E$21,4,FALSE) | F14: =VLOOKUP(A14,PriceList!$A$4:$E$21,5,FALSE) | G14: =D14*F14
A15: ENV-005 | B15: =VLOOKUP(A15,PriceList!$A$4:$E$21,3,FALSE) | C15: =VLOOKUP(A15,PriceList!$A$4:$E$21,2,FALSE) | D15: =Schedule!$B$12 | E15: =VLOOKUP(A15,PriceList!$A$4:$E$21,4,FALSE) | F15: =VLOOKUP(A15,PriceList!$A$4:$E$21,5,FALSE) | G15: =D15*F15
A16: WIN-001 | B16: =VLOOKUP(A16,PriceList!$A$4:$E$21,3,FALSE) | C16: =VLOOKUP(A16,PriceList!$A$4:$E$21,2,FALSE) | D16: =Schedule!$B$15 | E16: =VLOOKUP(A16,PriceList!$A$4:$E$21,4,FALSE) | F16: =VLOOKUP(A16,PriceList!$A$4:$E$21,5,FALSE) | G16: =D16*F16
A17: WIN-010 | B17: =VLOOKUP(A17,PriceList!$A$4:$E$21,3,FALSE) | C17: =VLOOKUP(A17,PriceList!$A$4:$E$21,2,FALSE) | D17: =Schedule!$B$16 | E17: =VLOOKUP(A17,PriceList!$A$4:$E$21,4,FALSE) | F17: =VLOOKUP(A17,PriceList!$A$4:$E$21,5,FALSE) | G17: =D17*F17
A18: WIN-020 | B18: =VLOOKUP(A18,PriceList!$A$4:$E$21,3,FALSE) | C18: =VLOOKUP(A18,PriceList!$A$4:$E$21,2,FALSE) | D18: =Schedule!$B$17 | E18: =VLOOKUP(A18,PriceList!$A$4:$E$21,4,FALSE) | F18: =VLOOKUP(A18,PriceList!$A$4:$E$21,5,FALSE) | G18: =D18*F18
A19: SITE-01 | B19: =VLOOKUP(A19,PriceList!$A$4:$E$21,3,FALSE) | C19: =VLOOKUP(A19,PriceList!$A$4:$E$21,2,FALSE) | D19: =Parameters!$B$14 | E19: =VLOOKUP(A19,PriceList!$A$4:$E$21,4,FALSE) | F19: =VLOOKUP(A19,PriceList!$A$4:$E$21,5,FALSE) | G19: =D19*F19
A20: SITE-02 | B20: =VLOOKUP(A20,PriceList!$A$4:$E$21,3,FALSE) | C20: =VLOOKUP(A20,PriceList!$A$4:$E$21,2,FALSE) | D20: =Parameters!$B$14 | E20: =VLOOKUP(A20,PriceList!$A$4:$E$21,4,FALSE) | F20: =VLOOKUP(A20,PriceList!$A$4:$E$21,5,FALSE) | G20: =D20*F20
A21: SITE-10 | B21: =VLOOKUP(A21,PriceList!$A$4:$E$21,3,FALSE) | C21: =VLOOKUP(A21,PriceList!$A$4:$E$21,2,FALSE) | D21: =1 | E21: =VLOOKUP(A21,PriceList!$A$4:$E$21,4,FALSE) | F21: =VLOOKUP(A21,PriceList!$A$4:$E$21,5,FALSE) | G21: =D21*F21
A22: SITE-20 | B22: =VLOOKUP(A22,PriceList!$A$4:$E$21,3,FALSE) | C22: =VLOOKUP(A22,PriceList!$A$4:$E$21,2,FALSE) | D22: 35 | E22: =VLOOKUP(A22,PriceList!$A$4:$E$21,4,FALSE) | F22: =VLOOKUP(A22,PriceList!$A$4:$E$21,5,FALSE) | G22: =D22*F22
A25: AGGREGATION BY CATEGORY
A26: Category | B26: Description | G26: Cost subtotal EUR
A27: STR | B27: Structure (load-bearing timber, beams, slabs) | G27: =SUMIF(C5:C22,"STR",G5:G22)
A28: ENV | B28: Envelope (insulation, facade, roof package, flashings) | G28: =SUMIF(C5:C22,"ENV",G5:G22)
A29: WIN | B29: Windows, shutters, doors | G29: =SUMIF(C5:C22,"WIN",G5:G22)
A30: SITE | B30: Site management (crane, scaffolding, engineering, labour) | G30: =SUMIF(C5:C22,"SITE",G5:G22)
B31: TOTAL COST | G31: =SUM(G27:G30)
B32: Margin % | G32: =Parameters!$B$4
B33: SELLING PRICE (excl. VAT) | G33: =G31/(1-G32)
B34: VAT (21%) | G34: =G33*Parameters!$B$5
B35: TOTAL incl. VAT | G35: =G33+G34
